{
	"close":false,
	"natures":["egretProject"],
	"resourcePlugin":{
		"configs":[{
				"configPath":"resource/resource.json",
				"relativePath":"resource/"
			}],
		"id":"org.egret-labs.resource",
		"library":{
			"children":[
				{
					"isFolder":false,
					"key":"green",
					"name":"green"
				},
				{
					"isFolder":false,
					"key":"hand",
					"name":"hand"
				},
				{
					"isFolder":false,
					"key":"icon",
					"name":"icon"
				},
				{
					"children":[
						{
							"isFolder":false,
							"key":"car1",
							"name":"car1"
						},
						{
							"isFolder":false,
							"key":"carmarks1",
							"name":"carmarks1"
						},
						{
							"isFolder":false,
							"key":"carmarks2",
							"name":"carmarks2"
						},
						{
							"isFolder":false,
							"key":"initcar",
							"name":"initcar"
						},
						{
							"isFolder":false,
							"key":"line1",
							"name":"line1"
						},
						{
							"isFolder":false,
							"key":"line2",
							"name":"line2"
						}
					],
					"isFolder":false,
					"key":"initscene",
					"name":"initscene"
				},
				{
					"isFolder":false,
					"key":"luzhang",
					"name":"luzhang"
				},
				{
					"isFolder":false,
					"key":"luzhangkuang",
					"name":"luzhangkuang"
				},
				{
					"isFolder":false,
					"key":"share_p0",
					"name":"share_p0"
				},
				{
					"isFolder":false,
					"key":"MZloadingImg",
					"name":"MZloadingImg"
				},
				{
					"isFolder":false,
					"key":"boattexturepng",
					"name":"boattexturepng"
				},
				{
					"isFolder":false,
					"key":"items/png",
					"name":"items/png"
				},
				{
					"isFolder":false,
					"key":"scorePanel",
					"name":"scorePanel"
				},
				{
					"isFolder":false,
					"key":"cloud",
					"name":"cloud"
				}
			]
		}
	}
}